colorama_ex/__init__.py
colorama_ex/ansi_ex_back.py
colorama_ex/ansi_ex_fore.py
colorama_ex/demo_24112023.py
colorama_EX-0.4.6.256.dist-info/METADATA
colorama_EX-0.4.6.256.dist-info/WHEEL
colorama_EX-0.4.6.256.dist-info/top_level.txt
colorama_EX-0.4.6.256.dist-info/RECORD
